modelling_utils/__init__.py
modelling_utils/data.py
modelling_utils/read.py
modelling_utils/utils.py
modelling_utils/write.py
modelling_utils-0.2.11.dist-info/LICENSE
modelling_utils-0.2.11.dist-info/WHEEL
modelling_utils-0.2.11.dist-info/METADATA
modelling_utils-0.2.11.dist-info/RECORD
