Metadata-Version: 2.1
Name: modelling-utils
Version: 0.2.11
Summary:  Utility functions and data structure for aiding in Analog Integrated Circuit Modelling using Python
Home-page: https://github.com/das-dias/modelling_utils
License: MIT
Keywords: modelling,analog-ic,python,gm-over-id,cmos
Author: Diogo André
Author-email: das.dias6@gmail.com
Requires-Python: >=3.9,<3.11
Classifier: License :: OSI Approved :: MIT License
Classifier: Programming Language :: Python :: 3
Classifier: Programming Language :: Python :: 3.10
Classifier: Programming Language :: Python :: 3.9
Requires-Dist: PyYAML (>=6.0,<7.0)
Requires-Dist: cycler (>=0.11.0,<0.12.0)
Requires-Dist: loguru (>=0.6.0,<0.7.0)
Requires-Dist: matplotlib (>=3.5.2,<4.0.0)
Requires-Dist: numpy (>=1.22.3,<2.0.0)
Requires-Dist: pandas (>=1.4.2,<2.0.0)
Requires-Dist: seaborn (>=0.11.2,<0.12.0)
Requires-Dist: toml (>=0.10.2,<0.11.0)
Project-URL: Repository, https://github.com/das-dias/modelling_utils
